{
	"miniprogramRoot": "dist/",
	"projectname": "mini-app",
	"description": "todo",
	"appid": "wxc61503cbaa6d2213",
	"setting": {
		"urlCheck": false,
		"es6": false,
		"postcss": false,
		"minified": false,
		"newFeature": true,
		"coverView": true,
		"autoAudits": false,
		"showShadowRootInWxmlPanel": true,
		"scopeDataCheck": false,
		"checkInvalidKey": true,
		"checkSiteMap": true,
		"uploadWithSourceMap": true,
		"babelSetting": {
			"ignore": [],
			"disablePlugins": [],
			"outputPath": ""
		}
	},
	"compileType": "miniprogram",
	"simulatorType": "wechat",
	"simulatorPluginLibVersion": {},
	"scripts": {
		"beforeCompile": "",
		"beforePreview": "npm run compress",
		"beforeUpload": ""
	},
	"condition": {}
}